LICENSE
MANIFEST.in
README.md
requirements.txt
setup.py
fastapi_serve/__init__.py
fastapi_serve/__main__.py
fastapi_serve/config.yml
fastapi_serve/helper.py
fastapi_serve.egg-info/PKG-INFO
fastapi_serve.egg-info/SOURCES.txt
fastapi_serve.egg-info/dependency_links.txt
fastapi_serve.egg-info/entry_points.txt
fastapi_serve.egg-info/not-zip-safe
fastapi_serve.egg-info/requires.txt
fastapi_serve.egg-info/top_level.txt
fastapi_serve/cloud/__init__.py
fastapi_serve/cloud/build.py
fastapi_serve/cloud/config.py
fastapi_serve/cloud/deploy.py
fastapi_serve/cloud/errors.py
fastapi_serve/cloud/export.py
fastapi_serve/cloud/helper.py
fastapi_serve/cloud/options.py
fastapi_serve/gateway/__init__.py
fastapi_serve/gateway/gateway.py
fastapi_serve/gateway/helper.py
fastapi_serve/utils/__init__.py
fastapi_serve/utils/auth.py
fastapi_serve/utils/helper.py
fastapi_serve/utils/blob/__init__.py
fastapi_serve/utils/blob/storage.py