Metadata-Version: 2.1
Name: fastapi-serve
Version: 0.0.5
Summary: FastAPI Serve - FastAPI to the Cloud, Batteries Included!
Home-page: https://github.com/jina-ai/fastapi-serve/
Author: Jina AI
Author-email: hello@jina.ai
License: Apache 2.0
Download-URL: https://github.com/jina-ai/fastapi-serve/tags
Project-URL: Documentation, https://docs.jina.ai
Project-URL: Source, https://github.com/jina-ai/fastapi-serve/
Project-URL: Tracker, https://github.com/jina-ai/fastapi-serve/issues
Keywords: jina fastapi restapi cloud docker kubernetes
Platform: UNKNOWN
Classifier: Development Status :: 5 - Production/Stable
Classifier: Intended Audience :: Developers
Classifier: Intended Audience :: Education
Classifier: Intended Audience :: Science/Research
Classifier: Programming Language :: Python :: 3.7
Classifier: Programming Language :: Python :: 3.8
Classifier: Programming Language :: Python :: 3.9
Classifier: Programming Language :: Python :: 3.10
Classifier: Environment :: Console
Classifier: License :: OSI Approved :: Apache Software License
Classifier: Operating System :: OS Independent
Classifier: Topic :: Scientific/Engineering :: Artificial Intelligence
Provides-Extra: test
